{
  "composition": {
    "_name": "Title (atom)",
    "_id": "23d2d19c-a74c-48cd-b397-e1574bb84b7b",
    "type": "text",
    "parameters": {
      "tag": {
        "type": "dex-segmented-control-parameter",
        "value": "h1"
      },
      "font": {
        "type": "dex-token-selector-parameter",
        "value": "primary"
      },
      "size": {
        "type": "dex-segmented-control-parameter",
        "value": {
          "mobile": "3xl",
          "tablet": "4xl",
          "desktop": "4xl"
        }
      },
      "color": {
        "type": "dex-color-palette-parameter",
        "value": "text-primary"
      },
      "weight": {
        "type": "dex-segmented-control-parameter",
        "value": "bold"
      },
      "transform": {
        "type": "dex-segmented-control-parameter",
        "value": "uppercase"
      }
    },
    "_overridability": {
      "parameters": {
        "tag": "yes",
        "text": "yes"
      },
      "hideLockedParameters": true
    },
    "_locales": [
      "en-us",
      "es-us",
      "fr-ca",
      "en-ca",
      "en-gb",
      "de-de",
      "en-nz",
      "de-at",
      "nl-nl",
      "en-nl",
      "da-dk",
      "sv-se",
      "nb-no",
      "fr-fr",
      "en-au",
      "ja-jp",
      "ar-uae",
      "ar-ksa"
    ]
  },
  "created": "2025-05-20T11:53:41.843267+00:00",
  "modified": "2025-07-31T12:51:30.746178+00:00",
  "pattern": true,
  "categoryId": "70d03350-bbf9-457d-abc0-cf7d7aa2a3a4"
}